pofuzzy_helper/__init__.py
pofuzzy_helper/_version.py
pofuzzy_helper/cli.py
pofuzzy_helper/core.py
pofuzzy_helper/gui.py
pofuzzy_helper-0.1.2.dist-info/METADATA
pofuzzy_helper-0.1.2.dist-info/WHEEL
pofuzzy_helper-0.1.2.dist-info/entry_points.txt
pofuzzy_helper-0.1.2.dist-info/top_level.txt
pofuzzy_helper-0.1.2.dist-info/RECORD
