Metadata-Version: 2.4
Name: pofuzzy_helper
Version: 0.1.2
Summary: Helping translators to find differences in msgids between versions
Author-email: Christophe Nanteuil <christophe.nanteuil@gmail.com>
License-Expression: MIT
Project-URL: Homepage, https://git.afpy.org/ChristopheNan/pofuzzy_helper
Project-URL: Repository, https://git.afpy.org/ChristopheNan/pofuzzy_helper.git
Keywords: poutils,gettext,i18n
Classifier: Development Status :: 3 - Alpha
Classifier: Intended Audience :: Developers
Classifier: Natural Language :: English
Classifier: Programming Language :: Python :: 3
Classifier: Operating System :: OS Independent
Requires-Python: >=3.10
Requires-Dist: pygit2
Requires-Dist: tkinterweb
Provides-Extra: cli
Provides-Extra: dev
Requires-Dist: black; extra == "dev"
Requires-Dist: tox; extra == "dev"
Requires-Dist: coverage; extra == "dev"
